cli.py
icloud_hme/__init__.py
icloud_hme/hidemyemail.py
icloud_hme/icloud_auth.py
icloud_hme-1.0.0.dist-info/licenses/LICENSE
icloud_hme-1.0.0.dist-info/METADATA
icloud_hme-1.0.0.dist-info/WHEEL
icloud_hme-1.0.0.dist-info/entry_points.txt
icloud_hme-1.0.0.dist-info/top_level.txt
icloud_hme-1.0.0.dist-info/RECORD
