Metadata-Version: 2.4
Name: icloud-hme
Version: 1.0.0
Summary: Generate and manage iCloud+ HideMyEmail addresses from the command line
Author-email: GlizzyKingDreko <glizzykingdreko@protonmail.com>
License: MIT
Project-URL: Homepage, https://github.com/glizzykingdreko/icloud-hidemymail-generator
Project-URL: Repository, https://github.com/glizzykingdreko/icloud-hidemymail-generator
Project-URL: Issues, https://github.com/glizzykingdreko/icloud-hidemymail-generator/issues
Keywords: icloud,hidemyemail,email,generator,apple,privacy,alias
Classifier: Development Status :: 4 - Beta
Classifier: Environment :: Console
Classifier: Intended Audience :: Developers
Classifier: Intended Audience :: End Users/Desktop
Classifier: License :: OSI Approved :: MIT License
Classifier: Operating System :: OS Independent
Classifier: Programming Language :: Python :: 3
Classifier: Programming Language :: Python :: 3.8
Classifier: Programming Language :: Python :: 3.9
Classifier: Programming Language :: Python :: 3.10
Classifier: Programming Language :: Python :: 3.11
Classifier: Programming Language :: Python :: 3.12
Classifier: Topic :: Communications :: Email
Classifier: Topic :: Utilities
Requires-Python: >=3.8
License-File: LICENSE
Requires-Dist: requests>=2.31.0
Requires-Dist: srp>=1.0.21
Requires-Dist: click>=8.1.0
Requires-Dist: rich>=13.0.0
Dynamic: license-file
